lab1/lab1.1.4/sc2_block.v
module sc_block(s, c, a, b);
  output  s, c;
  input   a, b;
  wire    w1, w2, not_a, not_b;
  // the "c" output is just the AND of the two inputs
  and a1(c, a, b);
  // the "s" output is 1 only when exactly one of the inputs is 1
  not n1(not_a, a);
  not n2(not_b, b);
  and a2(w1, a, not_b);
  and a3(w2, b, not_a);
  or  o1(s, w1, w2);
endmodule // sc_block

// Implement sc2_block in Verilog as shown in the specification
// Use multiple instances of sc_block in sc_block2
module sc2_block(S, Cout, A, B, Cin);
  output  S, Cout;
  input   A, B, Cin;

  // ADD YOUR CODE HERE
  wire s1_out, c1_out, c2_out;
  sc_block block1(s1_out, c1_out, A, B);
  sc_block block2(S, c2_out, s1_out, Cin);
  or o2(Cout, c2_out, c1_out);



endmodule // sc2_block

lab1/lab1.1.4/sc2_block_tb.v
module test;

   // these are inputs to "circuit under test"
   reg A=0;
   reg B=0;
   reg Cin=0;
  
   // wires for the outputs of "circuit under test"
   wire S, Cout;
  
   // the circuit under test
   sc2_block sc2(S, Cout, A, B, Cin);  
    
   initial begin               // initial = run at beginning of simulation
                               // begin/end = associate block with initial
      
      $dumpfile("sc2_block.vcd");  // name of dump file to create
      $dumpvars(0, test);     // record all signals of module "test" and sub-modules
                              // remember to change "test" to the correct
                              // module name when writing your own test benches

      // test all input combinations
      A = 0; B = 0; Cin = 0; #10
      A = 0; B = 0; Cin = 1; #10
      A = 0; B = 1; Cin = 0; #10
      A = 0; B = 1; Cin = 1; #10
      A = 1; B = 0; Cin = 0; #10
      A = 1; B = 0; Cin = 1; #10
      A = 1; B = 1; Cin = 0; #10
      A = 1; B = 1; Cin = 1; #10
          
      $finish;        // end the simulation
   end                      
   
   initial begin
     $display("inputs = A B Cin  outputs = S Cout");
     $monitor("inputs = %b %b %b  outputs = %b %b   ",
              A, B, Cin, S, Cout);
   end
endmodule // test

lab1/lab1.1.4/sc2_block.vcd
$date
	Thu Aug 29 22:37:01 2024
$end
$version
	Icarus Verilog
$end
$timescale
	1s
$end
$scope module test $end
$var wire 1 ! S $end
$var wire 1 " Cout $end
$var reg 1 # A $end
$var reg 1 $ B $end
$var reg 1 % Cin $end
$scope module sc2 $end
$var wire 1 # A $end
$var wire 1 $ B $end
$var wire 1 % Cin $end
$var wire 1 " Cout $end
$var wire 1 & s1_out $end
$var wire 1 ' c2_out $end
$var wire 1 ( c1_out $end
$var wire 1 ! S $end
$scope module block1 $end
$var wire 1 # a $end
$var wire 1 $ b $end
$var wire 1 ( c $end
$var wire 1 ) not_a $end
$var wire 1 * not_b $end
$var wire 1 & s $end
$var wire 1 + w1 $end
$var wire 1 , w2 $end
$upscope $end
$scope module block2 $end
$var wire 1 & a $end
$var wire 1 % b $end
$var wire 1 ' c $end
$var wire 1 - not_a $end
$var wire 1 . not_b $end
$var wire 1 ! s $end
$var wire 1 / w1 $end
$var wire 1 0 w2 $end
$upscope $end
$upscope $end
$upscope $end
$enddefinitions $end
#0
$dumpvars
00
0/
1.
1-
0,
0+
1*
1)
0(
0'
0&
0%
0$
0#
0"
0!
$end
#10
1!
0.
10
1%
#20
0-
1/
1!
1&
1.
00
0*
1,
0%
1$
#30
0!
1"
0/
1'
0.
1%
#40
1!
1/
0-
0"
1+
1&
0'
1.
1*
0,
0)
0%
0$
1#
#50
0!
1"
0/
1'
0.
1%
#60
1-
0!
0&
0/
0+
0'
1.
1(
0*
0%
1$
#70
1!
0.
10
1%
