lab1/lab1.2.3/keypad.v
module keypad(valid, number, a, b, c, d, e, f, g);
   output   valid;
   output [3:0] number;
   input  a, b, c, d, e, f, g;

   assign valid = ~(((~a)&(~b)&(~c)&(~d)&(~e)&(~f)&(~g))| ((~a)&(~b)&c&(~d)&(~e)&(~f)&g)| (a&(~b)&(~c)&(~d)&(~e)&(~f)&g));
   assign number[3] = ((~a)&(~b)&c&(~d)&(~e)&f&(~g))|( (~a)&b&(~c)&(~d)&(~e)&f&(~g));
   assign number[2] = ((~a)&(~b)&c&(~d)&e&(~f)&(~g))|( (~a)&b&(~c)&(~d)&e&(~f)&(~g) )|( a&(~b)&(~c)&(~d)&(~e)&f&(~g) )|( a&(~b)&(~c)&(~d)&e&(~f)&(~g));
   assign number[1] = ((~a)&(~b)&c&(~d)&e&(~f)&(~g))|( (~a)&(~b)&c&d&(~e)&(~f)&(~g))|((~a)&b&(~c)&d&(~e)&(~f)&(~g))|(a&(~b)&(~c)&(~d)&(~e)&f&(~g));
   assign number[0] = ((~a)&(~b)&c&(~d)&(~e)&f&(~g))|( (~a)&(~b)&c&d&(~e)&(~f)&(~g)  )|( (~a)&b&(~c)&(~d)&e&(~f)&(~g) )|( a&(~b)&(~c)&(~d)&(~e)&f&(~g)  )|( a&(~b)&(~c)&d&(~e)&(~f)&(~g));

endmodule // keypad

lab1/lab1.2.3/keypad_tb.v
module keypad_test;

   reg a = 0, b = 0, c = 0;
   reg d = 0, e = 0, f = 0, g = 0;
   
   initial begin

      $dumpfile("kp.vcd");  
      $dumpvars(0,keypad_test);
      
      # 10  
    a = 1; d = 1;                // pressing 1
      # 10
    a = 0; b = 1;                // pressing 2
      # 10
    b = 0; c = 1;                // pressing 3
      # 10
    c = 0; d = 0;                
    a = 1; e = 1;                // pressing 4
      # 10
    a = 0; b = 1;                // pressing 5
      # 10
    b = 0; c = 1;                // pressing 6
      # 10
    c = 0; e = 0;                
    a = 1; f = 1;                // pressing 7
      # 10
    a = 0; b = 1;                // pressing 8
      # 10
    b = 0; c = 1;                // pressing 9
      # 10
    c = 0; f = 0;                
    b = 1; g = 1;                // pressing 0
      # 10 
    b = 0; g = 0;                // pressing nothing
      # 10 
      $finish;              // end the simulation
   end                      
   
   wire       valid;
   wire [3:0] number;
   keypad kp (valid, number, a, b, c, d, e, f, g);  

   wire [6:0]   inputs;
   assign inputs = {{ a, b, c, d, e, f, g }};  // this is syntax for grouping signals together as a bus.
           
   initial
     $monitor("At time %t, abcdefg = %x valid = %d number = %x",
              $time, inputs, valid, number);
endmodule // keypad_test

lab1/lab1.2.3/kp.vcd
$date
	Sun Sep  1 22:36:02 2024
$end
$version
	Icarus Verilog
$end
$timescale
	1s
$end
$scope module keypad_test $end
$var wire 1 ! valid $end
$var wire 4 " number [3:0] $end
$var wire 7 # inputs [6:0] $end
$var reg 1 $ a $end
$var reg 1 % b $end
$var reg 1 & c $end
$var reg 1 ' d $end
$var reg 1 ( e $end
$var reg 1 ) f $end
$var reg 1 * g $end
$scope module kp $end
$var wire 1 $ a $end
$var wire 1 % b $end
$var wire 1 & c $end
$var wire 1 ' d $end
$var wire 1 ( e $end
$var wire 1 ) f $end
$var wire 1 * g $end
$var wire 1 ! valid $end
$var wire 4 + number [3:0] $end
$upscope $end
$upscope $end
$enddefinitions $end
#0
$dumpvars
b0 +
0*
0)
0(
0'
0&
0%
0$
b0 #
b0 "
0!
$end
#10
1!
b1 "
b1 +
1'
b1001000 #
1$
#20
b10 "
b10 +
1%
b101000 #
0$
#30
b11 "
b11 +
1&
b11000 #
0%
#40
b100 "
b100 +
1(
1$
0'
b1000100 #
0&
#50
b101 "
b101 +
1%
b100100 #
0$
#60
b110 "
b110 +
1&
b10100 #
0%
#70
b111 "
b111 +
1)
1$
0(
b1000010 #
0&
#80
b1000 "
b1000 +
1%
b100010 #
0$
#90
b1001 "
b1001 +
1&
b10010 #
0%
#100
1!
b0 "
b0 +
1*
1%
0)
b100001 #
0&
#110
0!
0*
b0 #
0%
