lab1/lab1.1.2/sop_circuit.v
// Circuit implements the Boolean expression
// f(a,b,c,d) = a'b'c'd' + ab'c'd + ab'cd' + abcd

module sop_circuit(out, a, b, c, d);

// Port and wire declarations
output  out;
input   a, b, c, d;                               // output port
wire    out_a1, out_a2, out_a3, out_a4;    // and gate outputs
wire    not_a, not_b, not_c, not_d;        // not gate outputs

// NOT gates to create complements for product terms
not     na(not_a, a);
not     nb(not_b, b);
not     nc(not_c, c);
not     nd(not_d, d);

// AND gates to create product terms
and     a1(out_a1, not_a, not_b, not_c, not_d);
and     a2(out_a2, a, not_b, not_c, d);
and     a3(out_a3, a, not_b, c, not_d);
and     a4(out_a4, a, b, c, d);

// OR gate to combine outputs of AND gates
or      o1(out, out_a1, out_a2, out_a3, out_a4);
endmodule

lab1/lab1.1.2/sop_circuit_tb.v
module test;

   // these are inputs to "circuit under test"
   reg  a, b, c, d;

   // wires for the outputs of "circuit under test"
   wire out;
  
   // the circuit under test
   sop_circuit sop1(out, a, b, c, d);  
    
   initial begin               // initial = run at beginning of simulation
                               // begin/end = associate block with initial
      
      $dumpfile("test.vcd");  // name of dump file to create
      $dumpvars(0, test);     // record all signals of module "test" and sub-modules
                              // remember to change "test" to the correct
                              // module name when writing your own test benches

      // test all input combinations
      a = 0; b = 0; c = 0; d = 0; #10;
      a = 0; b = 0; c = 0; d = 1; #10;
      a = 0; b = 0; c = 1; d = 0; #10;
      a = 0; b = 0; c = 1; d = 1; #10;
      a = 0; b = 1; c = 0; d = 0; #10;
      a = 0; b = 1; c = 0; d = 1; #10;
      a = 0; b = 1; c = 1; d = 0; #10;
      a = 0; b = 1; c = 1; d = 1; #10;
      a = 1; b = 0; c = 0; d = 0; #10;
      a = 1; b = 0; c = 0; d = 1; #10;
      a = 1; b = 0; c = 1; d = 0; #10;
      a = 1; b = 0; c = 1; d = 1; #10;
      a = 1; b = 1; c = 0; d = 0; #10;
      a = 1; b = 1; c = 0; d = 1; #10;
      a = 1; b = 1; c = 1; d = 0; #10;
      a = 1; b = 1; c = 1; d = 1; #10;
      
      $finish;        // end the simulation
   end                      
   
   initial begin
     $display("inputs = in  outputs = out");
     $monitor("abcd = %b%b%b%b outputs = %b   time = %2t",
              a, b, c, d, out, $time);
   end
endmodule // test

lab1/lab1.1.2/test.vcd
$date
	Thu Aug 29 23:05:35 2024
$end
$version
	Icarus Verilog
$end
$timescale
	1s
$end
$scope module test $end
$var wire 1 ! out $end
$var reg 1 " a $end
$var reg 1 # b $end
$var reg 1 $ c $end
$var reg 1 % d $end
$scope module sop1 $end
$var wire 1 " a $end
$var wire 1 # b $end
$var wire 1 $ c $end
$var wire 1 % d $end
$var wire 1 & not_a $end
$var wire 1 ' not_b $end
$var wire 1 ( not_c $end
$var wire 1 ) not_d $end
$var wire 1 ! out $end
$var wire 1 * out_a1 $end
$var wire 1 + out_a2 $end
$var wire 1 , out_a3 $end
$var wire 1 - out_a4 $end
$upscope $end
$upscope $end
$enddefinitions $end
#0
$dumpvars
0-
0,
0+
1*
1)
1(
1'
1&
0%
0$
0#
0"
1!
$end
#10
0!
0*
0)
1%
#20
1)
0(
0%
1$
#30
0)
1%
#40
1)
1(
0'
0%
0$
1#
#50
0)
1%
#60
1)
0(
0%
1$
#70
0)
1%
#80
1)
1(
1'
0&
0%
0$
0#
1"
#90
1!
0)
1+
1%
#100
1,
1!
1)
0+
0(
0%
1$
#110
0!
0,
0)
1%
#120
1)
1(
0'
0%
0$
1#
#130
0)
1%
#140
1)
0(
0%
1$
#150
1!
0)
1-
1%
